nedo_vision_worker/__init__.py
nedo_vision_worker/bootstrap.py
nedo_vision_worker/cli.py
nedo_vision_worker/doctor.py
nedo_vision_worker/worker_service.py
nedo_vision_worker/config/ConfigurationManager.py
nedo_vision_worker/config/ConfigurationManagerInterface.py
nedo_vision_worker/config/DummyConfigurationManager.py
nedo_vision_worker/config/__init__.py
nedo_vision_worker/database/DatabaseManager.py
nedo_vision_worker/database/__init__.py
nedo_vision_worker/models/__init__.py
nedo_vision_worker/models/ai_model.py
nedo_vision_worker/models/auth.py
nedo_vision_worker/models/config.py
nedo_vision_worker/models/dataset_source.py
nedo_vision_worker/models/logs.py
nedo_vision_worker/models/ppe_detection.py
nedo_vision_worker/models/ppe_detection_label.py
nedo_vision_worker/models/restricted_area_violation.py
nedo_vision_worker/models/user.py
nedo_vision_worker/models/worker_source.py
nedo_vision_worker/models/worker_source_pipeline.py
nedo_vision_worker/models/worker_source_pipeline_config.py
nedo_vision_worker/models/worker_source_pipeline_debug.py
nedo_vision_worker/models/worker_source_pipeline_detection.py
nedo_vision_worker/protos/AIModelService_pb2.py
nedo_vision_worker/protos/AIModelService_pb2_grpc.py
nedo_vision_worker/protos/DatasetSourceService_pb2.py
nedo_vision_worker/protos/DatasetSourceService_pb2_grpc.py
nedo_vision_worker/protos/HumanDetectionService_pb2.py
nedo_vision_worker/protos/HumanDetectionService_pb2_grpc.py
nedo_vision_worker/protos/PPEDetectionService_pb2.py
nedo_vision_worker/protos/PPEDetectionService_pb2_grpc.py
nedo_vision_worker/protos/VisionWorkerService_pb2.py
nedo_vision_worker/protos/VisionWorkerService_pb2_grpc.py
nedo_vision_worker/protos/WorkerSourcePipelineService_pb2.py
nedo_vision_worker/protos/WorkerSourcePipelineService_pb2_grpc.py
nedo_vision_worker/protos/WorkerSourceService_pb2.py
nedo_vision_worker/protos/WorkerSourceService_pb2_grpc.py
nedo_vision_worker/protos/__init__.py
nedo_vision_worker-1.3.12.dist-info/METADATA
nedo_vision_worker-1.3.12.dist-info/WHEEL
nedo_vision_worker-1.3.12.dist-info/entry_points.txt
nedo_vision_worker-1.3.12.dist-info/top_level.txt
nedo_vision_worker-1.3.12.dist-info/RECORD
