Metadata-Version: 2.4
Name: nedo-vision-worker
Version: 1.3.12
Summary: Nedo Vision Worker Service Library for AI Vision Processing
Author-email: Willy Achmat Fauzi <willy.achmat@gmail.com>
Maintainer-email: Willy Achmat Fauzi <willy.achmat@gmail.com>
License-Expression: MIT
Project-URL: Homepage, https://gitlab.com/sindika/research/nedo-vision/nedo-vision-worker-service
Project-URL: Documentation, https://gitlab.com/sindika/research/nedo-vision/nedo-vision-worker-service/-/blob/main/README.md
Project-URL: Repository, https://gitlab.com/sindika/research/nedo-vision/nedo-vision-worker-service
Project-URL: Bug Reports, https://gitlab.com/sindika/research/nedo-vision/nedo-vision-worker-service/-/issues
Keywords: computer-vision,machine-learning,ai,worker-service,deep-learning,object-detection,neural-networks,video-processing
Classifier: Development Status :: 4 - Beta
Classifier: Intended Audience :: Developers
Classifier: Operating System :: OS Independent
Classifier: Operating System :: POSIX :: Linux
Classifier: Operating System :: Microsoft :: Windows
Classifier: Operating System :: MacOS
Classifier: Programming Language :: Python :: 3
Classifier: Programming Language :: Python :: 3 :: Only
Classifier: Programming Language :: Python :: 3.8
Classifier: Programming Language :: Python :: 3.9
Classifier: Programming Language :: Python :: 3.10
Classifier: Programming Language :: Python :: 3.11
Classifier: Programming Language :: Python :: 3.12
Classifier: Programming Language :: Python :: 3.13
Classifier: Topic :: Software Development :: Libraries :: Python Modules
Classifier: Topic :: Multimedia :: Video
Classifier: Topic :: Scientific/Engineering :: Artificial Intelligence
Classifier: Topic :: System :: Hardware
Classifier: Environment :: GPU
Classifier: Environment :: No Input/Output (Daemon)
Requires-Python: >=3.8
Requires-Dist: alembic>=1.8.0
Requires-Dist: ffmpeg-python>=0.2.0
Requires-Dist: grpcio>=1.50.0
Requires-Dist: pika>=1.3.0
Requires-Dist: protobuf>=3.20.0
Requires-Dist: psutil>=5.9.0
Requires-Dist: requests>=2.28.0
Requires-Dist: SQLAlchemy>=1.4.0
Requires-Dist: Pillow>=12.1.0
Requires-Dist: opencv-python-headless>=4.6.0
Requires-Dist: pynvml>=11.4.1; platform_system != "Darwin" or platform_machine != "arm64"
Provides-Extra: opencv
Requires-Dist: opencv-python>=4.6.0; extra == "opencv"
Provides-Extra: dev
Requires-Dist: pytest>=7.0.0; extra == "dev"
Requires-Dist: black>=22.0.0; extra == "dev"
Requires-Dist: isort>=5.10.0; extra == "dev"
Requires-Dist: mypy>=0.950; extra == "dev"
Requires-Dist: flake8>=4.0.0; extra == "dev"
Requires-Dist: pre-commit>=2.17.0; extra == "dev"
